salt_finder_charts/__init__.py
salt_finder_charts/cli.py
salt_finder_charts/ephemerides.py
salt_finder_charts/finder_chart.py
salt_finder_charts/image.py
salt_finder_charts/mode.py
salt_finder_charts/output.py
salt_finder_charts/position_angle.py
salt_finder_charts/standard_finder_charts.py
salt_finder_charts/util.py
salt_finder_charts/visibility.py
salt_finder_charts-0.3.7.dist-info/LICENSE
salt_finder_charts-0.3.7.dist-info/METADATA
salt_finder_charts-0.3.7.dist-info/WHEEL
salt_finder_charts-0.3.7.dist-info/entry_points.txt
salt_finder_charts-0.3.7.dist-info/top_level.txt
salt_finder_charts-0.3.7.dist-info/RECORD
