Metadata-Version: 2.1
Name: salt-finder-charts
Version: 0.3.7
Summary: Generate finder charts for the Southern African Large Telescope (SALT)
Home-page: https://github.com/saltastroops/salt_finder_charts
Author: SAAO/SALT
Author-email: salt-software@saao.ac.za
License: MIT license
Keywords: salt_finder_charts
Platform: UNKNOWN
Classifier: Development Status :: 2 - Pre-Alpha
Classifier: Intended Audience :: Developers
Classifier: License :: OSI Approved :: MIT License
Classifier: Natural Language :: English
Classifier: Programming Language :: Python :: 3
Classifier: Programming Language :: Python :: 3.5
Classifier: Programming Language :: Python :: 3.6
Classifier: Programming Language :: Python :: 3.7
Requires-Dist: aplpy
Requires-Dist: astropy
Requires-Dist: astroquery
Requires-Dist: Click
Requires-Dist: defusedxml
Requires-Dist: ephem
Requires-Dist: gilmenel
Requires-Dist: numpy
Requires-Dist: pillow
Requires-Dist: PyPDF2
Requires-Dist: pyregion
Requires-Dist: pytz
